ir/__init__.py
ir-0.0.6.dist-info/licenses/LICENSE
ir-0.0.6.dist-info/METADATA
ir-0.0.6.dist-info/WHEEL
ir-0.0.6.dist-info/top_level.txt
ir-0.0.6.dist-info/RECORD
