Metadata-Version: 2.4
Name: ir
Version: 0.0.6
Summary: amazon_sender.py
Home-page: https://github.com/t-c-w/ir
Author: Thor Whalen
License: apache-2.0
Platform: any
License-File: LICENSE
Dynamic: license-file
